sololearnlib/__init__.py
sololearnlib/sololearn.py
sololearnlib-3.0.0.dist-info/LICENSE.txt
sololearnlib-3.0.0.dist-info/METADATA
sololearnlib-3.0.0.dist-info/WHEEL
sololearnlib-3.0.0.dist-info/top_level.txt
sololearnlib-3.0.0.dist-info/RECORD
