Metadata-Version: 2.1
Name: sololearnlib
Version: 3.0.0
Summary: Retrieve public data from 'sololearn.com'.
Home-page: https://github.com/Or-i0n/sololearnlib
Author: OR!ON
Author-email: orionconner00@gmail.com
License: MIT
Platform: UNKNOWN
Classifier: Development Status :: 3 - Alpha
Classifier: Intended Audience :: Developers
Classifier: Topic :: Software Development :: Build Tools
Classifier: License :: OSI Approved :: MIT License
Classifier: Programming Language :: Python :: 3.5
Classifier: Programming Language :: Python :: 3.6
Classifier: Programming Language :: Python :: 3.7
Classifier: Programming Language :: Python :: 3.8
Requires-Python: >=3.5
Requires-Dist: bs4
